.clang-format
.dockerignore
.gitignore
.pre-commit-config.yaml
.readthedocs.yaml
.shellcheckrc
.yapfignore
CMakeLists.txt
CODE_OF_CONDUCT.md
CONTRIBUTING.md
DCO
Dockerfile.fixed
LICENSE
MANIFEST.in
README.md
RELEASE.md
SECURITY.md
find_cuda_init.py
fix_xgrammar_concurrency.py
format.sh
pyproject.toml
setup.py
use_existing_torch.py
.buildkite/check-wheel-size.py
.buildkite/generate_index.py
.buildkite/release-pipeline.yaml
.buildkite/test-pipeline.yaml
.buildkite/lm-eval-harness/run-lm-eval-gsm-hf-baseline.sh
.buildkite/lm-eval-harness/run-lm-eval-gsm-vllm-baseline.sh
.buildkite/lm-eval-harness/run-tests.sh
.buildkite/lm-eval-harness/test_lm_eval_correctness.py
.buildkite/lm-eval-harness/configs/DeepSeek-V2-Lite-Chat.yaml
.buildkite/lm-eval-harness/configs/Meta-Llama-3-70B-Instruct-FBGEMM-nonuniform.yaml
.buildkite/lm-eval-harness/configs/Meta-Llama-3-70B-Instruct.yaml
.buildkite/lm-eval-harness/configs/Meta-Llama-3-8B-Instruct-Channelwise-compressed-tensors.yaml
.buildkite/lm-eval-harness/configs/Meta-Llama-3-8B-Instruct-FBGEMM-nonuniform.yaml
.buildkite/lm-eval-harness/configs/Meta-Llama-3-8B-Instruct-FP8-compressed-tensors.yaml
.buildkite/lm-eval-harness/configs/Meta-Llama-3-8B-Instruct-FP8.yaml
.buildkite/lm-eval-harness/configs/Meta-Llama-3-8B-Instruct-INT8-compressed-tensors-asym.yaml
.buildkite/lm-eval-harness/configs/Meta-Llama-3-8B-Instruct-INT8-compressed-tensors.yaml
.buildkite/lm-eval-harness/configs/Meta-Llama-3-8B-Instruct-nonuniform-compressed-tensors.yaml
.buildkite/lm-eval-harness/configs/Meta-Llama-3-8B-Instruct.yaml
.buildkite/lm-eval-harness/configs/Meta-Llama-3-8B-QQQ.yaml
.buildkite/lm-eval-harness/configs/Meta-Llama-3.2-1B-Instruct-INT8-compressed-tensors.yaml
.buildkite/lm-eval-harness/configs/Minitron-4B-Base-FP8.yaml
.buildkite/lm-eval-harness/configs/Mixtral-8x22B-Instruct-v0.1-FP8-Dynamic.yaml
.buildkite/lm-eval-harness/configs/Mixtral-8x7B-Instruct-v0.1-FP8.yaml
.buildkite/lm-eval-harness/configs/Mixtral-8x7B-Instruct-v0.1.yaml
vllm_fixed.egg-info/PKG-INFO
vllm_fixed.egg-info/SOURCES.txt
vllm_fixed.egg-info/dependency_links.txt
vllm_fixed.egg-info/entry_points.txt
vllm_fixed.egg-info/requires.txt
vllm_fixed.egg-info/top_level.txt