Metadata-Version: 2.1
Name: vllm-fixed
Version: 1.0.0
Summary: A high-throughput and memory-efficient inference and serving engine for LLMs
Author: vLLM Team
License: Apache-2.0
Project-URL: Homepage, https://github.com/vllm-project/vllm
Project-URL: Documentation, https://vllm.readthedocs.io/en/latest/
Project-URL: Slack, http://slack.vllm.ai/
Classifier: Programming Language :: Python :: 3.9
Classifier: Programming Language :: Python :: 3.10
Classifier: Programming Language :: Python :: 3.11
Classifier: Programming Language :: Python :: 3.12
Classifier: Intended Audience :: Developers
Classifier: Intended Audience :: Information Technology
Classifier: Intended Audience :: Science/Research
Classifier: Topic :: Scientific/Engineering :: Artificial Intelligence
Classifier: Topic :: Scientific/Engineering :: Information Analysis
Requires-Python: <3.13,>=3.9
License-File: LICENSE
Requires-Dist: cachetools
Requires-Dist: psutil
Requires-Dist: sentencepiece
Requires-Dist: numpy
Requires-Dist: requests>=2.26.0
Requires-Dist: tqdm
Requires-Dist: blake3
Requires-Dist: py-cpuinfo
Requires-Dist: transformers>=4.51.1
Requires-Dist: huggingface-hub[hf_xet]>=0.30.0
Requires-Dist: tokenizers>=0.21.1
Requires-Dist: protobuf
Requires-Dist: fastapi[standard]>=0.115.0
Requires-Dist: aiohttp
Requires-Dist: openai>=1.52.0
Requires-Dist: pydantic>=2.9
Requires-Dist: prometheus_client>=0.18.0
Requires-Dist: pillow
Requires-Dist: prometheus-fastapi-instrumentator>=7.0.0
Requires-Dist: tiktoken>=0.6.0
Requires-Dist: lm-format-enforcer<0.11,>=0.10.11
Requires-Dist: llguidance<0.8.0,>=0.7.9; platform_machine == "x86_64" or platform_machine == "arm64" or platform_machine == "aarch64"
Requires-Dist: outlines==0.1.11
Requires-Dist: lark==1.2.2
Requires-Dist: xgrammar==0.1.18; platform_machine == "x86_64" or platform_machine == "aarch64"
Requires-Dist: typing_extensions>=4.10
Requires-Dist: filelock>=3.16.1
Requires-Dist: partial-json-parser
Requires-Dist: pyzmq>=25.0.0
Requires-Dist: msgspec
Requires-Dist: gguf>=0.13.0
Requires-Dist: importlib_metadata
Requires-Dist: mistral_common[opencv]>=1.5.4
Requires-Dist: opencv-python-headless>=4.11.0
Requires-Dist: pyyaml
Requires-Dist: six>=1.16.0; python_version > "3.11"
Requires-Dist: setuptools>=74.1.1; python_version > "3.11"
Requires-Dist: einops
Requires-Dist: compressed-tensors==0.9.3
Requires-Dist: depyf==0.18.0
Requires-Dist: cloudpickle
Requires-Dist: watchfiles
Requires-Dist: python-json-logger
Requires-Dist: scipy
Requires-Dist: ninja
Requires-Dist: opentelemetry-sdk<1.27.0,>=1.26.0
Requires-Dist: opentelemetry-api<1.27.0,>=1.26.0
Requires-Dist: opentelemetry-exporter-otlp<1.27.0,>=1.26.0
Requires-Dist: opentelemetry-semantic-conventions-ai<0.5.0,>=0.4.1
Requires-Dist: torch==2.6.0+cpu; platform_machine == "x86_64"
Requires-Dist: torch==2.6.0; platform_system == "Darwin"
Requires-Dist: torch==2.6.0; platform_machine == "ppc64le" or platform_machine == "aarch64"
Requires-Dist: torch==2.7.0.dev20250304; platform_machine == "s390x"
Requires-Dist: torchaudio; platform_machine != "ppc64le" and platform_machine != "s390x"
Requires-Dist: torchaudio==2.6.0; platform_machine == "ppc64le"
Requires-Dist: torchvision; platform_machine != "ppc64le" and platform_machine != "s390x"
Requires-Dist: torchvision==0.21.0; platform_machine == "ppc64le"
Requires-Dist: datasets
Requires-Dist: triton==3.2.0; platform_machine == "x86_64"
Provides-Extra: tensorizer
Requires-Dist: tensorizer>=2.9.0; extra == "tensorizer"
Provides-Extra: fastsafetensors
Requires-Dist: fastsafetensors>=0.1.10; extra == "fastsafetensors"
Provides-Extra: runai
Requires-Dist: runai-model-streamer; extra == "runai"
Requires-Dist: runai-model-streamer-s3; extra == "runai"
Requires-Dist: boto3; extra == "runai"
Provides-Extra: audio
Requires-Dist: librosa; extra == "audio"
Requires-Dist: soundfile; extra == "audio"
Provides-Extra: video
